cellarr_array/__init__.py
cellarr_array/core/__init__.py
cellarr_array/core/base.py
cellarr_array/core/dense.py
cellarr_array/core/helpers.py
cellarr_array/core/sparse.py
cellarr_array/dataloaders/__init__.py
cellarr_array/dataloaders/denseloader.py
cellarr_array/dataloaders/iterabledataloader.py
cellarr_array/dataloaders/sparseloader.py
cellarr_array/dataloaders/utils.py
cellarr_array/utils/__init__.py
cellarr_array/utils/config.py
cellarr_array/utils/mock.py
cellarr_array-0.3.3.dist-info/licenses/LICENSE.txt
cellarr_array-0.3.3.dist-info/METADATA
cellarr_array-0.3.3.dist-info/WHEEL
cellarr_array-0.3.3.dist-info/top_level.txt
cellarr_array-0.3.3.dist-info/RECORD
