Metadata-Version: 2.4
Name: cellarr-array
Version: 0.3.3
Summary: Base class for handling TileDB backed arrays.
Home-page: https://github.com/cellarr/cellarr-array
Author: Jayaram Kancherla
Author-email: jayaram.kancherla@gmail.com
License: MIT
Project-URL: Documentation, https://github.com/cellarr/cellarr-array
Project-URL: Source, https://github.com/cellarr/cellarr-array
Platform: any
Classifier: Development Status :: 4 - Beta
Classifier: Programming Language :: Python
License-File: LICENSE.txt
Requires-Dist: importlib-metadata; python_version < "3.8"
Requires-Dist: tiledb
Requires-Dist: numpy
Requires-Dist: scipy
Provides-Extra: optional
Requires-Dist: torch; extra == "optional"
Provides-Extra: testing
Requires-Dist: setuptools; extra == "testing"
Requires-Dist: pytest; extra == "testing"
Requires-Dist: pytest-cov; extra == "testing"
Requires-Dist: pandas; extra == "testing"
Requires-Dist: torch; extra == "testing"
Dynamic: license-file
